fedcloudclient/__init__.py
fedcloudclient/checkin.py
fedcloudclient/cli.py
fedcloudclient/decorators.py
fedcloudclient/ec3.py
fedcloudclient/endpoint.py
fedcloudclient/openstack.py
fedcloudclient/schema.json
fedcloudclient/secret.py
fedcloudclient/select.py
fedcloudclient/shell.py
fedcloudclient/sites.py
fedcloudclient-1.4.4.data/scripts/list-all-my-own-vms.sh
fedcloudclient-1.4.4.data/scripts/list-my-own-vms.sh
fedcloudclient-1.4.4.dist-info/AUTHORS
fedcloudclient-1.4.4.dist-info/LICENSE
fedcloudclient-1.4.4.dist-info/METADATA
fedcloudclient-1.4.4.dist-info/WHEEL
fedcloudclient-1.4.4.dist-info/entry_points.txt
fedcloudclient-1.4.4.dist-info/pbr.json
fedcloudclient-1.4.4.dist-info/top_level.txt
fedcloudclient-1.4.4.dist-info/RECORD
