Metadata-Version: 2.1
Name: fedcloudclient
Version: 1.4.4
Summary: EGI FedCloud client
Home-page: https://fedcloudclient.fedcloud.eu/
Author: Viet Tran, Enol Fernandez
Author-email: tdviet@gmail.com
Classifier: Intended Audience :: Information Technology
Classifier: Intended Audience :: Science/Research
Classifier: License :: OSI Approved :: MIT License
Classifier: Operating System :: OS Independent
Classifier: Programming Language :: Python :: 3
Classifier: Topic :: Utilities
Classifier: Topic :: Software Development :: Libraries :: Python Modules
Classifier: Development Status :: 5 - Production/Stable
Classifier: Environment :: OpenStack
License-File: LICENSE
License-File: AUTHORS
Requires-Dist: click==8.1.7
Requires-Dist: click-option-group==0.5.6
Requires-Dist: tabulate==0.9.0
Requires-Dist: requests==2.31.0
Requires-Dist: defusedxml~=0.7.1
Requires-Dist: pyjwt==2.8.0
Requires-Dist: python-openstackclient==6.3.0
Requires-Dist: liboidcagent==0.6.0
Requires-Dist: jsonpath-ng==1.6.0
Requires-Dist: PyYAML==6.0.1
Requires-Dist: setuptools==68.2.2
Requires-Dist: jsonschema==4.19.2
Requires-Dist: psutil==5.9.6
Requires-Dist: hvac==2.0.0
Requires-Dist: cryptography==42.0.4
